{
  "colors": {
    "Cursor": { "bg": "#d0d0d0", "fg": "#161616" },
    "TermCursor": { "bg": "#d0d0d0", "fg": "#161616" },
    "@error": { "bg": "NONE", "fg": "#33b1ff" },
    "BufferLineDiagnosticVisible": {
      "fg": "#ee5396",
      "bold": true,
      "bg": "NONE"
    },
    "Normal": { "bg": "#161616", "fg": "#d0d0d0" },
    "TelescopeNormal": { "bg": "#131313", "fg": "NONE" },
    "NotifyERRORTitle": { "bg": "NONE", "fg": "#3ddbd9" },
    "@symbol": { "fg": "#82cfff", "bold": true, "bg": "NONE" },
    "CmpItemKindInterface": { "bg": "#3ddbd9", "fg": "#262626" },
    "@number.status": { "bg": "NONE", "fg": "#ff7eb6" },
    "NotifyTRACETitle": { "bg": "NONE", "fg": "#42be65" },
    "@keyword.function": { "bg": "NONE", "fg": "#3ddbd9" },
    "DiffDelete": { "fg": "NONE", "bg": "#361c28" },
    "ColorColumn": { "bg": "#262626", "fg": "NONE" },
    "@label": { "bg": "NONE", "fg": "#82cfff" },
    "Conditional": { "bg": "NONE", "fg": "#78a9ff" },
    "Character": { "bg": "NONE", "fg": "#be95ff" },
    "StorageClass": { "bg": "NONE", "fg": "#78a9ff" },
    "@text.strike": { "fg": "#ee5396", "strikethrough": true, "bg": "NONE" },
    "LspSignatureActiveParameter": { "bg": "NONE", "fg": "#3ddbd9" },
    "LineNr": { "bg": "#161616", "fg": "#525252" },
    "markdownListMarker": { "bg": "NONE", "fg": "#3ddbd9" },
    "DiffAdded": { "bg": "NONE", "fg": "#08bdba" },
    "CmpItemKindConstant": { "bg": "#ee5396", "fg": "#262626" },
    "@number.date": { "bg": "NONE", "fg": "#3ddbd9" },
    "BufferLineDiagnostic": { "fg": "#ee5396", "bold": true, "bg": "NONE" },
    "CodeBlock": { "bg": "#262626", "fg": "NONE" },
    "CmpItemKindTypeParameter": { "bg": "#3ddbd9", "fg": "#262626" },
    "alpha2": { "bg": "NONE", "fg": "#d0d0d0" },
    "Substitute": { "bg": "#3ddbd9", "fg": "#262626" },
    "StatusCommand": { "bg": "#42be65", "fg": "#161616" },
    "CmpItemKindProperty": { "bg": "#ff7eb6", "fg": "#262626" },vimvimvimvim
    "DiffChanged": { "bg": "NONE", "fg": "#78a9ff" },
    "TelescopeMatching": {
      "bg": "NONE",
      "fg": "#3ddbd9",
      "bold": true,
      "italic": true
    },
    "NvimTreeWinSeparator": { "bg": "#161616", "fg": "#161616" },
    "alpha1": { "bg": "NONE", "fg": "#525252" },
    "HydraHint": { "bg": "#131313", "fg": "NONE" },
    "Error": { "bg": "#262626", "fg": "#ee5396" },
    "Folded": { "bg": "#262626", "fg": "#393939" },
    "HydraTeal": { "bg": "NONE", "fg": "#3ddbd9" },
    "Type": { "bg": "NONE", "fg": "#78a9ff" },
    "HydraAmaranth": { "bg": "NONE", "fg": "#ee5396" },
    "Conceal": { "bg": "NONE", "fg": "NONE" },
    "@keyword": { "bg": "NONE", "fg": "#78a9ff" },
    "Number": { "bg": "NONE", "fg": "#82cfff" },
    "Label": { "bg": "NONE", "fg": "#78a9ff" },
    "Italic": { "fg": "NONE", "bg": "NONE", "italic": true },
    "StatusNormal": { "bg": "#82cfff", "fg": "#161616" },
    "NvimTreeIndentMarker": { "bg": "NONE", "fg": "#393939" },
    "HydraBlue": { "bg": "NONE", "fg": "#78a9ff" },
    "HydraRed": { "bg": "NONE", "fg": "#ff7eb6" },
    "@constant.builtin": { "bg": "NONE", "fg": "#08bdba" },
    "NotifyERRORBorder": { "bg": "NONE", "fg": "#3ddbd9" },
    "Operator": { "bg": "NONE", "fg": "#78a9ff" },
    "NeogitHunkHeaderHighlight": { "bg": "#525252", "fg": "#d0d0d0" },
    "Identifier": { "bg": "NONE", "fg": "#d0d0d0" },
    "helpSpecial": { "bg": "NONE", "fg": "#78a9ff" },
    "NeogitRemote": { "bg": "NONE", "fg": "#78a9ff" },
    "NeogitBranch": { "bg": "NONE", "fg": "#ee5396" },
    "DiffAdd": { "fg": "NONE", "bg": "#122f2f" },
    "NvimTreeNormal": { "bg": "#161616", "fg": "#d0d0d0" },
    "Tag": { "bg": "NONE", "fg": "#d0d0d0" },
    "NvimTreeOpenedFolderName": { "bg": "NONE", "fg": "#82cfff" },
    "Structure": { "bg": "NONE", "fg": "#78a9ff" },
    "StatusInsert": { "bg": "#ff7eb6", "fg": "#161616" },
    "@number.interval": { "bg": "NONE", "fg": "#78a9ff" },
    "MoreMsg": { "bg": "NONE", "fg": "#3ddbd9" },
    "NvimTreeFolderName": { "bg": "NONE", "fg": "#78a9ff" },
    "NvimTreeFolderIcon": { "bg": "NONE", "fg": "#ff7eb6" },
    "@reference": { "bg": "NONE", "fg": "#d0d0d0" },
    "markdownBlockquote": { "bg": "NONE", "fg": "#3ddbd9" },
    "Comment": { "fg": "#525252", "bg": "NONE", "italic": true },
    "TelescopeBorder": { "bg": "#131313", "fg": "#131313" },
    "CmpItemKindEnumMember": { "bg": "#82cfff", "fg": "#262626" },
    "NotifyWARNBorder": { "bg": "NONE", "fg": "#be95ff" },
    "helpHeader": { "bg": "NONE", "fg": "#82cfff" },
    "CmpItemKindFolder": { "bg": "#42be65", "fg": "#262626" },
    "asciidocAttributeEntry": { "bg": "NONE", "fg": "#82cfff" },
    "DiagnosticHint": { "bg": "NONE", "fg": "#d0d0d0" },
    "StatusLineDiagnosticError": {
      "fg": "#ee5396",
      "bold": true,
      "bg": "#161616"
    },
    "CmpItemKindMethod": { "bg": "#82cfff", "fg": "#262626" },
    "CmpItemKindFile": { "bg": "#be95ff", "fg": "#262626" },
    "PmenuSbar": { "bg": "#262626", "fg": "#d0d0d0" },
    "CmpItemKindVariable": { "bg": "#be95ff", "fg": "#262626" },
    "LspReferenceWrite": { "bg": "#525252", "fg": "NONE" },
    "DiagnosticWarn": { "bg": "NONE", "fg": "#be95ff" },
    "PmenuThumb": { "bg": "#393939", "fg": "#3ddbd9" },
    "CmpItemKindValue": { "bg": "#82cfff", "fg": "#262626" },
    "CmpItemAbbrMatch": { "fg": "#f2f2f2", "bold": true, "bg": "NONE" },
    "CmpItemKindUnit": { "bg": "#42be65", "fg": "#262626" },
    "helpHeadline": { "bg": "NONE", "fg": "#ee5396" },
    "CmpItemKindField": { "bg": "#ff7eb6", "fg": "#262626" },
    "Keyword": { "bg": "NONE", "fg": "#78a9ff" },
    "Exception": { "bg": "NONE", "fg": "#78a9ff" },
    "CmpItemKindEvent": { "bg": "#ff7eb6", "fg": "#262626" },
    "CmpItemKindOperator": { "bg": "#33b1ff", "fg": "#262626" },
    "Include": { "bg": "NONE", "fg": "#78a9ff" },
    "@text.literal": { "bg": "NONE", "fg": "#d0d0d0" },
    "VisualNOS": { "bg": "#393939", "fg": "NONE" },
    "ModeMsg": { "bg": "NONE", "fg": "#d0d0d0" },
    "NvimInternalError": { "bg": "#3ddbd9", "fg": "#161616" },
    "LspReferenceread": { "bg": "#525252", "fg": "NONE" },
    "Pmenu": { "bg": "#262626", "fg": "#d0d0d0" },
    "Typedef": { "bg": "NONE", "fg": "#78a9ff" },
    "markdownBoldItalic": {
      "bg": "NONE",
      "fg": "NONE",
      "bold": true,
      "italic": true
    },
    "@text.emphasis": { "fg": "#ee5396", "bold": true, "bg": "NONE" },
    "StatusLineDiagnosticWarn": {
      "fg": "#be95ff",
      "bold": true,
      "bg": "#161616"
    },
    "NotifyWARNTitle": { "bg": "NONE", "fg": "#be95ff" },
    "StatusTerminal": { "bg": "#33b1ff", "fg": "#161616" },
    "DiffChange": { "fg": "NONE", "bg": "#222a39" },
    "@variable.builtin": { "bg": "NONE", "fg": "#d0d0d0" },
    "CmpItemMenu": { "fg": "#d0d0d0", "bg": "NONE", "italic": true },
    "Bold": { "fg": "NONE", "bold": true, "bg": "NONE" },
    "CmpItemKindConstructor": { "bg": "#ee5396", "fg": "#262626" },
    "TelescopePreviewTitle": { "bg": "#ff7eb6", "fg": "#393939" },
    "TelescopePromptPrefix": { "bg": "#393939", "fg": "#3ddbd9" },
    "TelescopePromptNormal": { "bg": "#393939", "fg": "#f2f2f2" },
    "@text.underline": { "underline": true, "fg": "#ee5396", "bg": "NONE" },
    "TelescopeResultsTitle": { "bg": "#131313", "fg": "#131313" },
    "@punctuation.special": { "bg": "NONE", "fg": "#3ddbd9" },
    "Function": { "bg": "NONE", "fg": "#3ddbd9" },
    "HealthSuccess": { "bg": "NONE", "fg": "#42be65" },
    "@text.title": { "bg": "NONE", "fg": "#ee5396" },
    "ErrorMsg": { "bg": "NONE", "fg": "#ee5396" },
    "DiagnosticInfo": { "bg": "NONE", "fg": "#78a9ff" },
    "@namespace": { "bg": "NONE", "fg": "#08bdba" },
    "NotifyTRACEBorder": { "bg": "NONE", "fg": "#42be65" },
    "@number.quantity.negative": { "bg": "NONE", "fg": "#ee5396" },
    "@punctuation.bracket": { "bg": "NONE", "fg": "#3ddbd9" },
    "VertSplit": { "bg": "#161616", "fg": "#262626" },
    "alpha3": { "bg": "NONE", "fg": "#525252" },
    "helpHyperTextJump": { "bg": "NONE", "fg": "#3ddbd9" },
    "Search": { "bg": "#3ddbd9", "fg": "#262626" },
    "@keyword.operator": { "bg": "NONE", "fg": "#3ddbd9" },
    "CmpItemAbbrMatchFuzzy": { "fg": "#d0d0d0", "bold": true, "bg": "NONE" },
    "CmpItemKindSnippet": { "bg": "#42be65", "fg": "#262626" },
    "NotifyDEBUGIcon": { "bg": "NONE", "fg": "#42be65" },
    "@constructor": { "bg": "NONE", "fg": "#78a9ff" },
    "NonText": { "bg": "NONE", "fg": "#393939" },
    "@text.uri": { "underline": true, "fg": "#be95ff", "bg": "NONE" },
    "Directory": { "bg": "NONE", "fg": "#3ddbd9" },
    "Macro": { "bg": "NONE", "fg": "#08bdba" },
    "CmpItemKindStruct": { "bg": "#33b1ff", "fg": "#262626" },
    "CmpItemKindFunction": { "bg": "#33b1ff", "fg": "#262626" },
    "IncSearch": { "bg": "#ee5396", "fg": "#ffffff" },
    "DiffRemoved": { "bg": "NONE", "fg": "#ee5396" },
    "NotifyTRACEIcon": { "bg": "NONE", "fg": "#42be65" },
    "CmpItemAbbr": { "bg": "NONE", "fg": "#adadad" },
    "NotifyDEBUGTitle": { "bg": "NONE", "fg": "#42be65" },
    "SignColumn": { "bg": "#161616", "fg": "#262626" },
    "NvimTreeEmptyFolderName": { "bg": "NONE", "fg": "#82cfff" },
    "NotifyERRORIcon": { "bg": "NONE", "fg": "#3ddbd9" },
    "NotifyDEBUGBorder": { "bg": "NONE", "fg": "#42be65" },
    "DiagnosticUnderlineHint": {
      "fg": "#d0d0d0",
      "bg": "NONE",
      "undercurl": true
    },
    "Underlined": { "underline": true, "fg": "NONE", "bg": "NONE" },
    "NotifyINFOBorder": { "bg": "NONE", "fg": "#f2f2f2" },
    "TelescopePreviewLine": { "bg": "#262626", "fg": "NONE" },
    "CmpItemKindColor": { "bg": "#3ddbd9", "fg": "#262626" },
    "CmpItemKindText": { "bg": "#78a9ff", "fg": "#262626" },
    "@function": { "fg": "#ff7eb6", "bold": true, "bg": "NONE" },
    "CmpItemKindKeyword": { "bg": "#78a9ff", "fg": "#262626" },
    "@number.date.effective": { "bg": "NONE", "fg": "#42be65" },
    "TelescopePromptBorder": { "bg": "#393939", "fg": "#393939" },
    "@function.macro": { "bg": "NONE", "fg": "#08bdba" },
    "Constant": { "bg": "NONE", "fg": "#d0d0d0" },
    "WildMenu": { "bg": "#262626", "fg": "#3ddbd9" },
    "StatusLineNC": { "bg": "#262626", "fg": "#d0d0d0" },
    "LspReferenceText": { "bg": "#525252", "fg": "NONE" },
    "NormalNC": { "bg": "#161616", "fg": "#f2f2f2" },
    "@repeat": { "bg": "NONE", "fg": "#78a9ff" },
    "StatusReplace": { "bg": "#3ddbd9", "fg": "#161616" },
    "Decorator": { "bg": "NONE", "fg": "#ff7eb6" },
    "StatusLine": { "bg": "#161616", "fg": "#d0d0d0" },
    "TermCursorNC": { "bg": "#d0d0d0", "fg": "#161616" },
    "FloatBorder": { "bg": "#131313", "fg": "#131313" },
    "NormalFloat": { "bg": "#131313", "fg": "#f2f2f2" },
    "@method": { "bg": "NONE", "fg": "#08bdba" },
    "DiagnosticError": { "bg": "NONE", "fg": "#ee5396" },
    "NvimTreeImageFile": { "bg": "NONE", "fg": "#ff7eb6" },
    "@tag.delimiter": { "bg": "NONE", "fg": "#82cfff" },
    "@tag.attribute": { "bg": "NONE", "fg": "#82cfff" },
    "@attribute": { "bg": "NONE", "fg": "#82cfff" },
    "@tag": { "bg": "NONE", "fg": "#78a9ff" },
    "CmpItemKindModule": { "bg": "#33b1ff", "fg": "#262626" },
    "CmpItemKindEnum": { "bg": "#78a9ff", "fg": "#262626" },
    "markdownOrderedListMarker": { "bg": "NONE", "fg": "#3ddbd9" },
    "CmpItemKindReference": { "bg": "#ee5396", "fg": "#262626" },
    "@text": { "bg": "NONE", "fg": "#d0d0d0" },
    "PreProc": { "bg": "NONE", "fg": "#78a9ff" },
    "SpecialComment": { "bg": "NONE", "fg": "#3ddbd9" },
    "@constant": { "bg": "NONE", "fg": "#be95ff" },
    "Title": { "bg": "NONE", "fg": "#d0d0d0" },
    "@variable": { "bg": "NONE", "fg": "#d0d0d0" },
    "@property": { "bg": "NONE", "fg": "#ee5396" },
    "TooLong": { "bg": "#393939", "fg": "NONE" },
    "@field": { "bg": "NONE", "fg": "#d0d0d0" },
    "@string.regex": { "bg": "NONE", "fg": "#08bdba" },
    "@exception": { "bg": "NONE", "fg": "#82cfff" },
    "@include": { "bg": "NONE", "fg": "#78a9ff" },
    "DiagnosticUnderlineWarn": {
      "fg": "#be95ff",
      "bg": "NONE",
      "undercurl": true
    },
    "DiffText": { "fg": "NONE", "bg": "#2f3f5c" },
    "StatusVisual": { "bg": "#be95ff", "fg": "#161616" },
    "@text.strong": { "bg": "NONE", "fg": "NONE" },
    "@text.literal.commodity": { "bg": "NONE", "fg": "#42be65" },
    "Visual": { "bg": "#393939", "fg": "NONE" },
    "CursorLineNr": { "bg": "NONE", "fg": "#d0d0d0" },
    "DiagnosticUnderlineInfo": {
      "fg": "#d0d0d0",
      "bg": "NONE",
      "undercurl": true
    },
    "SpecialChar": { "bg": "NONE", "fg": "#d0d0d0" },
    "@number.quantity": { "bg": "NONE", "fg": "#33b1ff" },
    "HealthWarning": { "bg": "NONE", "fg": "#be95ff" },
    "Statement": { "bg": "NONE", "fg": "#78a9ff" },
    "Repeat": { "bg": "NONE", "fg": "#78a9ff" },
    "SpecialKey": { "bg": "NONE", "fg": "#525252" },
    "@conditional": { "bg": "NONE", "fg": "#78a9ff" },
    "Debug": { "bg": "NONE", "fg": "#42be65" },
    "CursorLine": { "bg": "#262626", "fg": "NONE" },
    "CmpItemKindClass": { "bg": "#33b1ff", "fg": "#262626" },
    "NotifyINFOIcon": { "bg": "NONE", "fg": "#f2f2f2" },
    "Special": { "bg": "NONE", "fg": "#d0d0d0" },
    "WarningMsg": { "bg": "NONE", "fg": "#be95ff" },
    "MatchParen": { "underline": true, "fg": "NONE", "bg": "#393939" },
    "Question": { "bg": "NONE", "fg": "#d0d0d0" },
    "@number": { "bg": "NONE", "fg": "#78a9ff" },
    "TelescopeSelection": { "bg": "#393939", "fg": "NONE" },
    "Boolean": { "bg": "NONE", "fg": "#78a9ff" },
    "DiagnosticUnderlineError": {
      "fg": "#ee5396",
      "bg": "NONE",
      "undercurl": true
    },
    "CursorColumn": { "bg": "#262626", "fg": "NONE" },
    "Define": { "bg": "NONE", "fg": "#78a9ff" },
    "TelescopePromptTitle": { "bg": "#33b1ff", "fg": "#393939" },
    "FoldColumn": { "bg": "#161616", "fg": "#262626" },
    "EndOfBuffer": { "bg": "NONE", "fg": "#262626" },
    "QuickFixLine": { "bg": "#262626", "fg": "NONE" },
    "NeogitHunkHeader": { "bg": "#393939", "fg": "#d0d0d0" },
    "HealthError": { "bg": "NONE", "fg": "#ee5396" },
    "@parameter": { "bg": "NONE", "fg": "#d0d0d0" },
    "NotifyINFOTitle": { "bg": "NONE", "fg": "#f2f2f2" },
    "NotifyWARNIcon": { "bg": "NONE", "fg": "#be95ff" },
    "@constant.macro": { "bg": "NONE", "fg": "#08bdba" },
    "Todo": { "bg": "NONE", "fg": "#42be65" },
    "PmenuSel": { "bg": "#393939", "fg": "#3ddbd9" },
    "markdownUrl": { "underline": true, "fg": "#be95ff", "bg": "NONE" },
    "markdownH1": { "bg": "NONE", "fg": "#ee5396" },
    "@function.builtin": { "bg": "NONE", "fg": "#ff7eb6" },
    "@string.escape": { "bg": "NONE", "fg": "#82cfff" },
    "Delimeter": { "bg": "NONE", "fg": "#ffffff" },
    "@punctuation.delimiter": { "bg": "NONE", "fg": "#3ddbd9" },
    "String": { "bg": "NONE", "fg": "#be95ff" }
  },
  "links": {
    "@lsp.typemod.variable.static": "@constant",
    "@lsp.typemod.function.builtin": "@function.builtin",
    "@lsp.type.type": "Type",
    "@lsp.type.macro": "Macro",
    "mkdListItem": "markdownListMarker",
    "asciidocQuotedMonospaced": "markdownBlockquote",
    "VimwikiHeader3": "markdownH1",
    "@lsp.type.property": "@property",
    "@lsp.typemod.enum.defaultLibrary": "@type.builtin",
    "@lsp.mod.typeHint": "Type",
    "TabLineFill": "TabLine",
    "@lsp.typemod.method.defaultLibrary": "@function.builtin",
    "@lsp.typemod.operator.controlFlow": "@exception",
    "@lsp.type.typeAlias": "@type.definition",
    "@lsp.typemod.enumMember.defaultLibrary": "@constant.builtin",
    "@lsp.type.enum": "@type",
    "@lsp.mod.readonly": "@constant",
    "markdownCodeDelimiter": "markdownCode",
    "markdownH3": "markdownH1",
    "@comment": "Comment",
    "@lsp.type.decorator": "Decorator",
    "@lsp.typemod.function.readonly": "@method",
    "@lsp.type.builtinConstant": "@constant.builtin",
    "VimwikiList": "markdownListMarker",
    "@lsp.type.unresolvedReference": "Error",
    "@lsp.type.keyword": "@keyword",
    "@lsp.type.selfParameter": "@variable.builtin",
    "markdownH4": "markdownH1",
    "TabLine": "StatusLineNC",
    "Float": "Number",
    "VimwikiCode": "markdownCode",
    "markdownH2": "markdownH1",
    "VimwikiLink": "markdownUrl",
    "asciidocAttributeList": "asciidocAttributeEntry",
    "mkdRule": "markdownRule",
    "VimwikiHeader2": "markdownH1",
    "markdownBold": "Bold",
    "VimwikiHeader5": "markdownH1",
    "VimwikiHeader4": "markdownH1",
    "VimwikiHeader1": "markdownH1",
    "@lsp.type.class": "Structure",
    "mkdListItemCheckbox": "markdownListMarker",
    "VimwikiHeaderChar": "markdownH1",
    "@lsp.typemod.variable.injected": "@variable",
    "htmlH1": "markdownH1",
    "TabLineSel": "StatusLine",
    "@type.builtin": "Type",
    "@type": "Type",
    "asciidocURL": "markdownUrl",
    "@lsp.mod.builtin": "Special",
    "@lsp.typemod.variable.defaultLibrary": "@variable.builtin",
    "@boolean": "Boolean",
    "@float": "Float",
    "@lsp.type.comment": "@comment",
    "@string": "String",
    "@lsp.type.magicFunction": "@function.builtin",
    "@operator": "Operator",
    "@character": "Character",
    "@lsp.typemod.string.injected": "@string",
    "@lsp.type.namespace": "@namespace",
    "markdownRule": "Comment",
    "@lsp.type.variable": "@variable",
    "@lsp.typemod.macro.defaultLibrary": "@function.builtin",
    "@lsp.type.typeParameter": "Typedef",
    "@lsp.type.parameter": "@parameter",
    "asciidocAttributeRef": "asciidocAttributeEntry",
    "@lsp.type.function": "@function",
    "VimwikiHeader6": "markdownH1",
    "markdownCodeBlock": "markdownCode",
    "markdownCode": "String",
    "@lsp.type.method": "@function",
    "@number": "Number",
    "@lsp.type.selfKeyword": "@variable.builtin",
    "@lsp.type.escapeSequence": "@string.escape",
    "@lsp.typemod.keyword.documentation": "Special",
    "markdownItalic": "Italic",
    "@lsp.typemod.operator.injected": "@operator",
    "@lsp.type.formatSpecifier": "@punctuation.special",
    "@lsp.typemod.variable.global": "@constant",
    "@lsp.type.number": "@number",
    "@lsp.type.operator": "@operator",
    "@lsp.type.enumMember": "@constant",
    "asciidocHLabel": "markdownH1",
    "asciidocOneLineTitle": "markdownH1",
    "markdownHeadingDelimiter": "markdownH1",
    "markdownHeadingRule": "markdownH1",
    "@lsp.type.string.rust": "@string",
    "@lsp.type.struct": "Structure",
    "@lsp.type.builtinType": "@type.builtin",
    "markdownUrl": "String",
    "markdownH6": "markdownH1",
    "@lsp.typemod.keyword.async": "@keyword.coroutine",
    "@lsp.typemod.function.defaultLibrary": "@function.builtin",
    "markdownH5": "markdownH1",
    "@lsp.typemod.class.defaultLibrary": "@type.builtin",
    "@lsp.type.boolean": "@boolean"
  }
}
